data/__init__.py
data/example_tweets.csv
model_codes/Attention.py
model_codes/BERT_predict.py
model_codes/LSTM_predict.py
model_codes/SVM_with_BERT_predict.py
model_codes/SVM_with_LSTM_predict.py
model_codes/__init__.py
model_codes/two_step_BERT_predict.py
model_codes/two_step_LSTM_predict.py
pred_data/__init__.py
pred_data/example_tweets_user_pred.csv
processing/__init__.py
processing/text_preprocessing.py
trained_models/.gitattributes
trained_models/__init__.py
trained_models/cong_politician_2020-3-12-2021-5-28_balanced_pre-w2v_tokenizer.pkl
trained_models/step2_model_svm_200tweets_bert.sav
trained_models/step2_model_svm_200tweets_lstm.sav
PolitiClassify-0.0.6.dist-info/LICENSE
PolitiClassify-0.0.6.dist-info/METADATA
PolitiClassify-0.0.6.dist-info/WHEEL
PolitiClassify-0.0.6.dist-info/top_level.txt
PolitiClassify-0.0.6.dist-info/RECORD
